django_joining.py
django_joining-0.3.dist-info/DESCRIPTION.rst
django_joining-0.3.dist-info/METADATA
django_joining-0.3.dist-info/RECORD
django_joining-0.3.dist-info/WHEEL
django_joining-0.3.dist-info/metadata.json
django_joining-0.3.dist-info/top_level.txt
