Metadata-Version: 2.0
Name: django-joining
Version: 0.3
Summary: Arbitrary django model joining
Home-page: https://github.com/aachurin/django_joining/
Author: Andrey Churin
Author-email: aachurin@gmail.com
License: UNKNOWN
Platform: UNKNOWN
Classifier: Development Status :: 4 - Beta
Classifier: Intended Audience :: Developers
Classifier: License :: OSI Approved :: GNU Lesser General Public License v3 or later (LGPLv3+)
Classifier: Operating System :: OS Independent
Classifier: Programming Language :: Python
Classifier: Programming Language :: Python :: 3
Classifier: Framework :: Django
Classifier: Framework :: Django :: 1.11
